aovec/AozoraCloner.py
aovec/AozoraParser.py
aovec/AozoraVecMaker.py
aovec/__init__.py
aovec/main.py
aovec/py.typed
aovec-1.2.1.dist-info/LICENSE
aovec-1.2.1.dist-info/METADATA
aovec-1.2.1.dist-info/WHEEL
aovec-1.2.1.dist-info/entry_points.txt
aovec-1.2.1.dist-info/top_level.txt
aovec-1.2.1.dist-info/RECORD
