Metadata-Version: 2.1
Name: aovec
Version: 1.2.1
Summary: Make Word2Vec from aozorabunko/aozorabunko
Home-page: https://github.com/eggplants/aovec
Author: eggplants
Author-email: w10776e8w@yahoo.co.jp
License: MIT
Platform: UNKNOWN
Classifier: License :: OSI Approved :: MIT License
Classifier: Programming Language :: Python
Classifier: Programming Language :: Python :: 3
Classifier: Programming Language :: Python :: 3 :: Only
Classifier: Programming Language :: Python :: 3.7
Classifier: Programming Language :: Python :: 3.8
Classifier: Programming Language :: Python :: 3.9
Classifier: Programming Language :: Python :: 3.10
Classifier: Programming Language :: Python :: Implementation :: CPython
Requires-Python: >=3.7
License-File: LICENSE
Requires-Dist: beautifulsoup4 (>=4.10.0)
Requires-Dist: gensim (>=4.0.1)
Requires-Dist: mecab-python3 (>=1.0.5)
Requires-Dist: python-Levenshtein (>=0.12.2)
Requires-Dist: types-beautifulsoup4 (>=4.10.14)
Provides-Extra: dev
Requires-Dist: black ; extra == 'dev'
Requires-Dist: flake8 ; extra == 'dev'
Requires-Dist: mypy ; extra == 'dev'
Requires-Dist: setuptools (>=46.4.0) ; extra == 'dev'
Requires-Dist: types-requests ; extra == 'dev'
